heatflow/__init__.py
heatflow/ops.py
heatflow/tensor.py
heatflow/utils.py
heatflow/nn/__init__.py
heatflow/nn/functional.py
heatflow/nn/parameter.py
heatflow/nn/modules/__init__.py
heatflow/nn/modules/linear.py
heatflow/nn/modules/module.py
heatflow/optim/__init__.py
heatflow/optim/sgd.py
heatflow/tools/__init__.py
heatflow/tools/datasets/__init__.py
heatflow/tools/datasets/get_datasets.py
heatflow/tools/datasets/mnist.py
tests/__init__.py
tests/functional_testing.py
tests/ops_test.py
tests/ops_testing.py
tests/tensor.py
heatflow-0.0.1.dist-info/LICENSE
heatflow-0.0.1.dist-info/METADATA
heatflow-0.0.1.dist-info/WHEEL
heatflow-0.0.1.dist-info/top_level.txt
heatflow-0.0.1.dist-info/RECORD
