Metadata-Version: 2.1
Name: heatflow
Version: 0.0.1
Summary: HeatFlow is a python framework to work with neural networks, tensor, etc.
Author: Satyam Mishra
Author-email: tubex998@gmail.com
Requires-Python: >=3.10
License-File: LICENSE
Requires-Dist: numpy >=1.19.5
Requires-Dist: numba >=0.51.1
Requires-Dist: tqdm >=4.55.1
Requires-Dist: requests >=2.26.0
